Workbook

Sheet Sheet1

Sheet Fractional Reserve
B1: Deposit | C1: Reserve | D1: Loans | E1: Revenues | F1: Cost | G1: Profit
A2: 1 | B2: 1000000 | C2: =B2*$J$2 -> 100000 | D2: =B2-C2 -> 900000 | E2: =+D2*$J$4 -> 45000 | F2: =B2*$J$3 -> 20000 | G2: =E2-F2 -> 25000 | I2: Fractional Percentage | J2: 0.1
A3: =+A2+1 -> 2 | B3: =D2 -> 900000 | C3: =B3*$J$2 -> 90000 | D3: =B3-C3 -> 810000 | E3: =+D3*$J$4 -> 40500 | F3: =B3*$J$3 -> 18000 | G3: =E3-F3 -> 22500 | I3: Interest Paid Deposits | J3: 0.02
A4: =+A3+1 -> 3 | B4: =D3 -> 810000 | C4: =B4*$J$2 -> 81000 | D4: =B4-C4 -> 729000 | E4: =+D4*$J$4 -> 36450 | F4: =B4*$J$3 -> 16200 | G4: =E4-F4 -> 20250 | I4: Interests Received Loans | J4: 0.05
A5: =+A4+1 -> 4 | B5: =D4 -> 729000 | C5: =B5*$J$2 -> 72900 | D5: =B5-C5 -> 656100 | E5: =+D5*$J$4 -> 32805 | F5: =B5*$J$3 -> 14580 | G5: =E5-F5 -> 18225
A6: =+A5+1 -> 5 | B6: =D5 -> 656100 | C6: =B6*$J$2 -> 65610 | D6: =B6-C6 -> 590490 | E6: =+D6*$J$4 -> 29524.5 | F6: =B6*$J$3 -> 13122 | G6: =E6-F6 -> 16402.5
A7: =+A6+1 -> 6 | B7: =D6 -> 590490 | C7: =B7*$J$2 -> 59049 | D7: =B7-C7 -> 531441 | E7: =+D7*$J$4 -> 26572.05 | F7: =B7*$J$3 -> 11809.8 | G7: =E7-F7 -> 14762.25
A8: =+A7+1 -> 7 | B8: =D7 -> 531441 | C8: =B8*$J$2 -> 53144.1 | D8: =B8-C8 -> 478296.9 | E8: =+D8*$J$4 -> 23914.845 | F8: =B8*$J$3 -> 10628.82 | G8: =E8-F8 -> 13286.025
A9: =+A8+1 -> 8 | B9: =D8 -> 478296.9 | C9: =B9*$J$2 -> 47829.69 | D9: =B9-C9 -> 430467.21 | E9: =+D9*$J$4 -> 21523.361 | F9: =B9*$J$3 -> 9565.938 | G9: =E9-F9 -> 11957.423
A10: =+A9+1 -> 9 | B10: =D9 -> 430467.21 | C10: =B10*$J$2 -> 43046.721 | D10: =B10-C10 -> 387420.49 | E10: =+D10*$J$4 -> 19371.024 | F10: =B10*$J$3 -> 8609.3442 | G10: =E10-F10 -> 10761.68 | I10: Kura Piedra Bank Earnings
A11: =+A10+1 -> 10 | B11: =D10 -> 387420.49 | C11: =B11*$J$2 -> 38742.049 | D11: =B11-C11 -> 348678.44 | E11: =+D11*$J$4 -> 17433.922 | F11: =B11*$J$3 -> 7748.4098 | G11: =E11-F11 -> 9685.5122 | I11: Total Revenues | J11: =E119 -> 449998.01
A12: =+A11+1 -> 11 | B12: =D11 -> 348678.44 | C12: =B12*$J$2 -> 34867.844 | D12: =B12-C12 -> 313810.6 | E12: =+D12*$J$4 -> 15690.53 | F12: =B12*$J$3 -> 6973.5688 | G12: =E12-F12 -> 8716.961 | I12: Total Cost | J12: =F119 -> 199999.11
A13: =+A12+1 -> 12 | B13: =D12 -> 313810.6 | C13: =B13*$J$2 -> 31381.06 | D13: =B13-C13 -> 282429.54 | E13: =+D13*$J$4 -> 14121.477 | F13: =B13*$J$3 -> 6276.2119 | G13: =E13-F13 -> 7845.2649 | I13: Total Profit | J13: =G119 -> 249998.89
A14: =+A13+1 -> 13 | B14: =D13 -> 282429.54 | C14: =B14*$J$2 -> 28242.954 | D14: =B14-C14 -> 254186.58 | E14: =+D14*$J$4 -> 12709.329 | F14: =B14*$J$3 -> 5648.5907 | G14: =E14-F14 -> 7060.7384
A15: =+A14+1 -> 14 | B15: =D14 -> 254186.58 | C15: =B15*$J$2 -> 25418.658 | D15: =B15-C15 -> 228767.92 | E15: =+D15*$J$4 -> 11438.396 | F15: =B15*$J$3 -> 5083.7317 | G15: =E15-F15 -> 6354.6646 | I15: Total Loans | J15: =D119 -> 8999960.1
A16: =+A15+1 -> 15 | B16: =D15 -> 228767.92 | C16: =B16*$J$2 -> 22876.792 | D16: =B16-C16 -> 205891.13 | E16: =+D16*$J$4 -> 10294.557 | F16: =B16*$J$3 -> 4575.3585 | G16: =E16-F16 -> 5719.1981 | I16: Total Reserves | J16: =C119 -> 999995.57
A17: =+A16+1 -> 16 | B17: =D16 -> 205891.13 | C17: =B17*$J$2 -> 20589.113 | D17: =B17-C17 -> 185302.02 | E17: =+D17*$J$4 -> 9265.1009 | F17: =B17*$J$3 -> 4117.8226 | G17: =E17-F17 -> 5147.2783
A18: =+A17+1 -> 17 | B18: =D17 -> 185302.02 | C18: =B18*$J$2 -> 18530.202 | D18: =B18-C18 -> 166771.82 | E18: =+D18*$J$4 -> 8338.5908 | F18: =B18*$J$3 -> 3706.0404 | G18: =E18-F18 -> 4632.5505 | I18: Loans to Reserves ratio | J18: =J15/J16 -> 9
A19: =+A18+1 -> 18 | B19: =D18 -> 166771.82 | C19: =B19*$J$2 -> 16677.182 | D19: =B19-C19 -> 150094.64 | E19: =+D19*$J$4 -> 7504.7318 | F19: =B19*$J$3 -> 3335.4363 | G19: =E19-F19 -> 4169.2954
A20: =+A19+1 -> 19 | B20: =D19 -> 150094.64 | C20: =B20*$J$2 -> 15009.464 | D20: =B20-C20 -> 135085.17 | E20: =+D20*$J$4 -> 6754.2586 | F20: =B20*$J$3 -> 3001.8927 | G20: =E20-F20 -> 3752.3659 | I20: Multiple | J20: =J15/$B$2 -> 8.9999601
A21: =+A20+1 -> 20 | B21: =D20 -> 135085.17 | C21: =B21*$J$2 -> 13508.517 | D21: =B21-C21 -> 121576.65 | E21: =+D21*$J$4 -> 6078.8327 | F21: =B21*$J$3 -> 2701.7034 | G21: =E21-F21 -> 3377.1293
A22: =+A21+1 -> 21 | B22: =D21 -> 121576.65 | C22: =B22*$J$2 -> 12157.665 | D22: =B22-C22 -> 109418.99 | E22: =+D22*$J$4 -> 5470.9495 | F22: =B22*$J$3 -> 2431.5331 | G22: =E22-F22 -> 3039.4164
A23: =+A22+1 -> 22 | B23: =D22 -> 109418.99 | C23: =B23*$J$2 -> 10941.899 | D23: =B23-C23 -> 98477.09 | E23: =+D23*$J$4 -> 4923.8545 | F23: =B23*$J$3 -> 2188.3798 | G23: =E23-F23 -> 2735.4747
A24: =+A23+1 -> 23 | B24: =D23 -> 98477.09 | C24: =B24*$J$2 -> 9847.709 | D24: =B24-C24 -> 88629.381 | E24: =+D24*$J$4 -> 4431.4691 | F24: =B24*$J$3 -> 1969.5418 | G24: =E24-F24 -> 2461.9273
A25: =+A24+1 -> 24 | B25: =D24 -> 88629.381 | C25: =B25*$J$2 -> 8862.9381 | D25: =B25-C25 -> 79766.443 | E25: =+D25*$J$4 -> 3988.3222 | F25: =B25*$J$3 -> 1772.5876 | G25: =E25-F25 -> 2215.7345
A26: =+A25+1 -> 25 | B26: =D25 -> 79766.443 | C26: =B26*$J$2 -> 7976.6443 | D26: =B26-C26 -> 71789.799 | E26: =+D26*$J$4 -> 3589.4899 | F26: =B26*$J$3 -> 1595.3289 | G26: =E26-F26 -> 1994.1611
A27: =+A26+1 -> 26 | B27: =D26 -> 71789.799 | C27: =B27*$J$2 -> 7178.9799 | D27: =B27-C27 -> 64610.819 | E27: =+D27*$J$4 -> 3230.5409 | F27: =B27*$J$3 -> 1435.796 | G27: =E27-F27 -> 1794.745
A28: =+A27+1 -> 27 | B28: =D27 -> 64610.819 | C28: =B28*$J$2 -> 6461.0819 | D28: =B28-C28 -> 58149.737 | E28: =+D28*$J$4 -> 2907.4869 | F28: =B28*$J$3 -> 1292.2164 | G28: =E28-F28 -> 1615.2705
A29: =+A28+1 -> 28 | B29: =D28 -> 58149.737 | C29: =B29*$J$2 -> 5814.9737 | D29: =B29-C29 -> 52334.763 | E29: =+D29*$J$4 -> 2616.7382 | F29: =B29*$J$3 -> 1162.9947 | G29: =E29-F29 -> 1453.7434
A30: =+A29+1 -> 29 | B30: =D29 -> 52334.763 | C30: =B30*$J$2 -> 5233.4763 | D30: =B30-C30 -> 47101.287 | E30: =+D30*$J$4 -> 2355.0643 | F30: =B30*$J$3 -> 1046.6953 | G30: =E30-F30 -> 1308.3691
A31: =+A30+1 -> 30 | B31: =D30 -> 47101.287 | C31: =B31*$J$2 -> 4710.1287 | D31: =B31-C31 -> 42391.158 | E31: =+D31*$J$4 -> 2119.5579 | F31: =B31*$J$3 -> 942.02574 | G31: =E31-F31 -> 1177.5322
A32: =+A31+1 -> 31 | B32: =D31 -> 42391.158 | C32: =B32*$J$2 -> 4239.1158 | D32: =B32-C32 -> 38152.042 | E32: =+D32*$J$4 -> 1907.6021 | F32: =B32*$J$3 -> 847.82317 | G32: =E32-F32 -> 1059.779
... A118: =+A117+1 -> 117 | B118: =D117 -> 4.9218808 | C118: =B118*$J$2 -> 0.49218808 | D118: =B118-C118 -> 4.4296928 | E118: =+D118*$J$4 -> 0.22148464 | F118: =B118*$J$3 -> 0.098437617 | G118: =E118-F118 -> 0.12304702
B119: =SUM(B2:B118) -> 9999955.7 | C119: =SUM(C2:C118) -> 999995.57 | D119: =SUM(D2:D118) -> 8999960.1 | E119: =SUM(E2:E118) -> 449998.01 | F119: =SUM(F2:F118) -> 199999.11 | G119: =SUM(G2:G118) -> 249998.89

Sheet Fractional Reserve Products
B1: Deposit | C1: Reserve | D1: Loans | E1: Revenues | F1: Cost | G1: Profit
A2: 1 | B2: 1000000 | C2: =B2*$J$2 -> 100000 | D2: =B2-C2 -> 900000 | E2: =+D2*$J$4 -> 45000 | F2: =B2*$J$3 -> 20000 | G2: =E2-F2 -> 25000 | I2: Fractional Percentage | J2: 0.1
A3: =+A2+1 -> 2 | B3: =D2 -> 900000 | C3: =B3*$J$2 -> 90000 | D3: =B3-C3 -> 810000 | E3: =+D3*$J$5 -> 48600 | F3: =B3*$J$3 -> 18000 | G3: =E3-F3 -> 30600 | I3: Interest Paid Deposits | J3: 0.02
A4: =+A3+1 -> 3 | B4: =D3 -> 810000 | C4: =B4*$J$2 -> 81000 | D4: =B4-C4 -> 729000 | E4: =+D4*$J$6 -> 72900 | F4: =B4*$J$3 -> 16200 | G4: =E4-F4 -> 56700 | I4: Interests Received Mortgage | J4: 0.05
A5: =+A4+1 -> 4 | B5: =D4 -> 729000 | C5: =B5*$J$2 -> 72900 | D5: =B5-C5 -> 656100 | E5: =+D5*$J$7 -> 131220 | F5: =B5*$J$3 -> 14580 | G5: =E5-F5 -> 116640 | I5: Interest Received Car Loans | J5: 0.06
A6: =+A5+1 -> 5 | B6: =D5 -> 656100 | C6: =B6*$J$2 -> 65610 | D6: =B6-C6 -> 590490 | E6: =+D6*$J$7 -> 118098 | F6: =B6*$J$3 -> 13122 | G6: =E6-F6 -> 104976 | I6: Interest Received Business Loans | J6: 0.1
A7: =+A6+1 -> 6 | B7: =D6 -> 590490 | C7: =B7*$J$2 -> 59049 | D7: =B7-C7 -> 531441 | E7: =+D7*$J$7 -> 106288.2 | F7: =B7*$J$3 -> 11809.8 | G7: =E7-F7 -> 94478.4 | I7: Interest Received Credit Cards | J7: 0.2
A8: =+A7+1 -> 7 | B8: =D7 -> 531441 | C8: =B8*$J$2 -> 53144.1 | D8: =B8-C8 -> 478296.9 | E8: =+D8*$J$7 -> 95659.38 | F8: =B8*$J$3 -> 10628.82 | G8: =E8-F8 -> 85030.56
A9: =+A8+1 -> 8 | B9: =D8 -> 478296.9 | C9: =B9*$J$2 -> 47829.69 | D9: =B9-C9 -> 430467.21 | E9: =+D9*$J$7 -> 86093.442 | F9: =B9*$J$3 -> 9565.938 | G9: =E9-F9 -> 76527.504
A10: =+A9+1 -> 9 | B10: =D9 -> 430467.21 | C10: =B10*$J$2 -> 43046.721 | D10: =B10-C10 -> 387420.49 | E10: =+D10*$J$7 -> 77484.098 | F10: =B10*$J$3 -> 8609.3442 | G10: =E10-F10 -> 68874.754 | I10: Kura Piedra Bank Earnings
A11: =+A10+1 -> 10 | B11: =D10 -> 387420.49 | C11: =B11*$J$2 -> 38742.049 | D11: =B11-C11 -> 348678.44 | E11: =+D11*$J$7 -> 69735.688 | F11: =B11*$J$3 -> 7748.4098 | G11: =E11-F11 -> 61987.278 | I11: Total Revenues | J11: =E119 -> 1478692
A12: =+A11+1 -> 11 | B12: =D11 -> 348678.44 | C12: =B12*$J$2 -> 34867.844 | D12: =B12-C12 -> 313810.6 | E12: =+D12*$J$7 -> 62762.119 | F12: =B12*$J$3 -> 6973.5688 | G12: =E12-F12 -> 55788.55 | I12: Total Cost | J12: =F119 -> 199999.11
A13: =+A12+1 -> 12 | B13: =D12 -> 313810.6 | C13: =B13*$J$2 -> 31381.06 | D13: =B13-C13 -> 282429.54 | E13: =+D13*$J$7 -> 56485.907 | F13: =B13*$J$3 -> 6276.2119 | G13: =E13-F13 -> 50209.695 | I13: Total Profit | J13: =G119 -> 1278692.9
A14: =+A13+1 -> 13 | B14: =D13 -> 282429.54 | C14: =B14*$J$2 -> 28242.954 | D14: =B14-C14 -> 254186.58 | E14: =+D14*$J$7 -> 50837.317 | F14: =B14*$J$3 -> 5648.5907 | G14: =E14-F14 -> 45188.726 | I14: ,
A15: =+A14+1 -> 14 | B15: =D14 -> 254186.58 | C15: =B15*$J$2 -> 25418.658 | D15: =B15-C15 -> 228767.92 | E15: =+D15*$J$7 -> 45753.585 | F15: =B15*$J$3 -> 5083.7317 | G15: =E15-F15 -> 40669.853 | I15: Total Loans | J15: =D119 -> 8999960.1
A16: =+A15+1 -> 15 | B16: =D15 -> 228767.92 | C16: =B16*$J$2 -> 22876.792 | D16: =B16-C16 -> 205891.13 | E16: =+D16*$J$7 -> 41178.226 | F16: =B16*$J$3 -> 4575.3585 | G16: =E16-F16 -> 36602.868 | I16: Total Reserves | J16: =C119 -> 999995.57
A17: =+A16+1 -> 16 | B17: =D16 -> 205891.13 | C17: =B17*$J$2 -> 20589.113 | D17: =B17-C17 -> 185302.02 | E17: =+D17*$J$7 -> 37060.404 | F17: =B17*$J$3 -> 4117.8226 | G17: =E17-F17 -> 32942.581
A18: =+A17+1 -> 17 | B18: =D17 -> 185302.02 | C18: =B18*$J$2 -> 18530.202 | D18: =B18-C18 -> 166771.82 | E18: =+D18*$J$7 -> 33354.363 | F18: =B18*$J$3 -> 3706.0404 | G18: =E18-F18 -> 29648.323 | I18: Loans to Reserves ratio | J18: =J15/J16 -> 9
A19: =+A18+1 -> 18 | B19: =D18 -> 166771.82 | C19: =B19*$J$2 -> 16677.182 | D19: =B19-C19 -> 150094.64 | E19: =+D19*$J$7 -> 30018.927 | F19: =B19*$J$3 -> 3335.4363 | G19: =E19-F19 -> 26683.491
A20: =+A19+1 -> 19 | B20: =D19 -> 150094.64 | C20: =B20*$J$2 -> 15009.464 | D20: =B20-C20 -> 135085.17 | E20: =+D20*$J$7 -> 27017.034 | F20: =B20*$J$3 -> 3001.8927 | G20: =E20-F20 -> 24015.142 | I20: Multiple | J20: =J15/$B$2 -> 8.9999601
A21: =+A20+1 -> 20 | B21: =D20 -> 135085.17 | C21: =B21*$J$2 -> 13508.517 | D21: =B21-C21 -> 121576.65 | E21: =+D21*$J$7 -> 24315.331 | F21: =B21*$J$3 -> 2701.7034 | G21: =E21-F21 -> 21613.627
A22: =+A21+1 -> 21 | B22: =D21 -> 121576.65 | C22: =B22*$J$2 -> 12157.665 | D22: =B22-C22 -> 109418.99 | E22: =+D22*$J$7 -> 21883.798 | F22: =B22*$J$3 -> 2431.5331 | G22: =E22-F22 -> 19452.265
A23: =+A22+1 -> 22 | B23: =D22 -> 109418.99 | C23: =B23*$J$2 -> 10941.899 | D23: =B23-C23 -> 98477.09 | E23: =+D23*$J$7 -> 19695.418 | F23: =B23*$J$3 -> 2188.3798 | G23: =E23-F23 -> 17507.038
A24: =+A23+1 -> 23 | B24: =D23 -> 98477.09 | C24: =B24*$J$2 -> 9847.709 | D24: =B24-C24 -> 88629.381 | E24: =+D24*$J$7 -> 17725.876 | F24: =B24*$J$3 -> 1969.5418 | G24: =E24-F24 -> 15756.334
A25: =+A24+1 -> 24 | B25: =D24 -> 88629.381 | C25: =B25*$J$2 -> 8862.9381 | D25: =B25-C25 -> 79766.443 | E25: =+D25*$J$7 -> 15953.289 | F25: =B25*$J$3 -> 1772.5876 | G25: =E25-F25 -> 14180.701
A26: =+A25+1 -> 25 | B26: =D25 -> 79766.443 | C26: =B26*$J$2 -> 7976.6443 | D26: =B26-C26 -> 71789.799 | E26: =+D26*$J$7 -> 14357.96 | F26: =B26*$J$3 -> 1595.3289 | G26: =E26-F26 -> 12762.631
A27: =+A26+1 -> 26 | B27: =D26 -> 71789.799 | C27: =B27*$J$2 -> 7178.9799 | D27: =B27-C27 -> 64610.819 | E27: =+D27*$J$7 -> 12922.164 | F27: =B27*$J$3 -> 1435.796 | G27: =E27-F27 -> 11486.368
A28: =+A27+1 -> 27 | B28: =D27 -> 64610.819 | C28: =B28*$J$2 -> 6461.0819 | D28: =B28-C28 -> 58149.737 | E28: =+D28*$J$7 -> 11629.947 | F28: =B28*$J$3 -> 1292.2164 | G28: =E28-F28 -> 10337.731
A29: =+A28+1 -> 28 | B29: =D28 -> 58149.737 | C29: =B29*$J$2 -> 5814.9737 | D29: =B29-C29 -> 52334.763 | E29: =+D29*$J$7 -> 10466.953 | F29: =B29*$J$3 -> 1162.9947 | G29: =E29-F29 -> 9303.9579
A30: =+A29+1 -> 29 | B30: =D29 -> 52334.763 | C30: =B30*$J$2 -> 5233.4763 | D30: =B30-C30 -> 47101.287 | E30: =+D30*$J$7 -> 9420.2574 | F30: =B30*$J$3 -> 1046.6953 | G30: =E30-F30 -> 8373.5621
A31: =+A30+1 -> 30 | B31: =D30 -> 47101.287 | C31: =B31*$J$2 -> 4710.1287 | D31: =B31-C31 -> 42391.158 | E31: =+D31*$J$7 -> 8478.2317 | F31: =B31*$J$3 -> 942.02574 | G31: =E31-F31 -> 7536.2059
A32: =+A31+1 -> 31 | B32: =D31 -> 42391.158 | C32: =B32*$J$2 -> 4239.1158 | D32: =B32-C32 -> 38152.042 | E32: =+D32*$J$7 -> 7630.4085 | F32: =B32*$J$3 -> 847.82317 | G32: =E32-F32 -> 6782.5853
... A118: =+A117+1 -> 117 | B118: =D117 -> 4.9218808 | C118: =B118*$J$2 -> 0.49218808 | D118: =B118-C118 -> 4.4296928 | E118: =+D118*$J$7 -> 0.88593855 | F118: =B118*$J$3 -> 0.098437617 | G118: =E118-F118 -> 0.78750093
B119: =SUM(B2:B118) -> 9999955.7 | C119: =SUM(C2:C118) -> 999995.57 | D119: =SUM(D2:D118) -> 8999960.1 | E119: =SUM(E2:E118) -> 1478692 | F119: =SUM(F2:F118) -> 199999.11 | G119: =SUM(G2:G118) -> 1278692.9

Sheet Bank Statements
G2: Kura Piedra Bank
D3: Balansa (Balance) | L3: Ganashi/Perdidat (Profit & Loss / Earnings)
B4: Propiedat (Assets) | F4: Debe (Liabilities) | J4: Entrada (Revenues) | N4: Gastu (Expenditutes
A7: Hypotheek | B7: ='Fractional Reserve Products'!D2 -> 900000 | J7: Pago Hypotheek | K7: ='Fractional Reserve Products'!E2 -> 45000 | N7: Interes deposito | O7: =SUM('Fractional Reserve Products'!F2:F118) -> 199999.11
A8: Fiansa di Auto | B8: ='Fractional Reserve Products'!D3 -> 810000 | J8: Pago Fiansa Auto | K8: ='Fractional Reserve Products'!E3 -> 48600
A9: Fiansa di Negoshi | B9: ='Fractional Reserve Products'!D4 -> 729000 | J9: Pago Fiansa Negoshi | K9: ='Fractional Reserve Products'!E4 -> 72900
A10: Fiansa di Credit cards | B10: =SUM('Fractional Reserve Products'!D5:D118) -> 6560960.1 | J10: Pago di Fiansa di Credit Cards | K10: =SUM('Fractional Reserve Products'!E5:E118) -> 1312192
N13: Saldo | O13: =O16-O7 -> 1278692.9
A16: Total | B16: =SUM(B7:B10) -> 8999960.1 | F16: Total | G16: =B16 -> 8999960.1 | J16: Total | K16: =SUM(K7:K10) -> 1478692 | N16: Total | O16: =K16 -> 1478692
C24: Bo Famia | L24: Bo Famia
D26: Balansa (Balance) | L26: Ganashi/Perdidat (Profit & Loss / Earnings)
B27: Propiedat (Assets) | F27: Debe (Liabilities) | J27: Entrada (Revenues) | N27: Gastu (Expenditutes
A30: Kas | F30: Hypotheek | G30: =B7 -> 900000 | J30: Interes deposito | K30: =O7 -> 199999.11 | N30: Pago Hypotheek | O30: =K7 -> 45000
A31: Auto | F31: Fiansa di Auto | G31: =B8 -> 810000 | N31: Pago Fiansa Auto | O31: =K8 -> 48600
A32: Negoshi | F32: Fiansa di Negoshi | G32: =B9 -> 729000 | N32: Pago Fiansa Negoshi | O32: =K9 -> 72900
F33: Fiansa di Credit cards | G33: =B10 -> 6560960.1 | N33: Pago di Fiansa di Credit Cards | O33: =K10 -> 1312192
F39: Total | G39: =SUM(G30:G33) -> 8999960.1 | J39: Saldo | K39: =K30-K41 -> -1278692.9
J41: Total | K41: =O41 -> 1478692 | N41: Total | O41: =SUM(O30:O33) -> 1478692
